prefab_pb2.py
sdk_reforge/VERSION
sdk_reforge/__init__.py
sdk_reforge/_count_down_latch.py
sdk_reforge/_internal_constants.py
sdk_reforge/_internal_logging.py
sdk_reforge/_requests.py
sdk_reforge/_sse_connection_manager.py
sdk_reforge/_telemetry.py
sdk_reforge/config_loader.py
sdk_reforge/config_parser.py
sdk_reforge/config_resolver.py
sdk_reforge/config_sdk.py
sdk_reforge/config_sdk_interface.py
sdk_reforge/config_value_unwrapper.py
sdk_reforge/config_value_wrapper.py
sdk_reforge/constants.py
sdk_reforge/context.py
sdk_reforge/context_shape.py
sdk_reforge/context_shape_aggregator.py
sdk_reforge/encryption.py
sdk_reforge/feature_flag_sdk.py
sdk_reforge/log_level.py
sdk_reforge/logging.py
sdk_reforge/options.py
sdk_reforge/read_write_lock.py
sdk_reforge/sdk.py
sdk_reforge/semantic_version.py
sdk_reforge/simple_criterion_evaluators.py
sdk_reforge/weighted_value_resolver.py
sdk_reforge/yaml_parser.py
sdk_reforge-1.1.0.dist-info/METADATA
sdk_reforge-1.1.0.dist-info/WHEEL
sdk_reforge-1.1.0.dist-info/licenses/LICENSE.txt
sdk_reforge-1.1.0.dist-info/RECORD
